{
  "runId": 375,
  "config_id": "375",
  "inputParameters": {
    "simulationType": "Monte-Carlo",
    "maxAllowedBlockchainLength": "30",
    "numberOfMonteCarloRounds": "1000",
    "blockchainSystemModelFilePath": "org.palladiosimulator.blockchainsystems.trilemma/testmodels/threesim-375/Net.blockchainsystem",
    "failureThroughputThreshold": "1.0",
    "shannonEntropyK": "1.0",
    "nakamotoCoefficientThreshold": "50.0",
    "reliabilityObservationTimespan": "24.0",
    "config_id": "375",
    "id": "375",
    "Hnode": "6.145057909",
    "Hlink": "8.937781266",
    "block_creation_interval": "597",
    "hashrate_concentration": "0.929850437",
    "max_block_size": "5",
    "inbound_connections": "80",
    "outbound_connections": "6",
    "validator_count": "1613",
    "number_of_attackers": "527"
  },
  "simulationResult": {
    "attackerWonRounds": 0,
    "systemWonRounds": 0,
    "unambiguousRounds": 1000
  },
  "startSimulationTime": 35841945614560,
  "stopSimulationTime": 35865145270935,
  "simulationTime": 23199656375,
  "memoryUsed": 1628
}