{
  "runId": 119,
  "config_id": "119",
  "inputParameters": {
    "simulationType": "Monte-Carlo",
    "maxAllowedBlockchainLength": "30",
    "numberOfMonteCarloRounds": "1000",
    "blockchainSystemModelFilePath": "org.palladiosimulator.blockchainsystems.trilemma/testmodels/threesim-119/Net.blockchainsystem",
    "failureThroughputThreshold": "1.0",
    "shannonEntropyK": "1.0",
    "nakamotoCoefficientThreshold": "50.0",
    "reliabilityObservationTimespan": "24.0",
    "config_id": "119",
    "id": "119",
    "Hnode": "9.064348883",
    "Hlink": "6.96755912",
    "block_creation_interval": "997",
    "hashrate_concentration": "0.502047743",
    "max_block_size": "6",
    "inbound_connections": "74",
    "outbound_connections": "14",
    "validator_count": "3856",
    "number_of_attackers": "485"
  },
  "simulationResult": {
    "attackerWonRounds": 0,
    "systemWonRounds": 0,
    "unambiguousRounds": 1000
  },
  "startSimulationTime": 28096932366124,
  "stopSimulationTime": 28142280372871,
  "simulationTime": 45348006747,
  "memoryUsed": 3490
}