{
  "runId": 198,
  "config_id": "198",
  "inputParameters": {
    "simulationType": "Monte-Carlo",
    "maxAllowedBlockchainLength": "10",
    "numberOfMonteCarloRounds": "1000",
    "blockchainSystemModelFilePath": "org.palladiosimulator.blockchainsystems.trilemma/testmodels/threesim-198/Net.blockchainsystem",
    "failureThroughputThreshold": "1.0",
    "shannonEntropyK": "1.0",
    "nakamotoCoefficientThreshold": "50.0",
    "reliabilityObservationTimespan": "24.0",
    "config_id": "198",
    "id": "198",
    "Hnode": "7.675631092",
    "Hlink": "7.871586051",
    "block_creation_interval": "934",
    "hashrate_concentration": "0.364574501",
    "max_block_size": "6",
    "inbound_connections": "140",
    "outbound_connections": "7",
    "validator_count": "161",
    "number_of_attackers": "25"
  },
  "simulationResult": {
    "attackerWonRounds": 0,
    "systemWonRounds": 0,
    "unambiguousRounds": 1000
  },
  "startSimulationTime": 352533612530209,
  "stopSimulationTime": 352575251849498,
  "simulationTime": 41639319289,
  "memoryUsed": 2765
}