{
  "runId": 364,
  "config_id": "364",
  "inputParameters": {
    "simulationType": "Monte-Carlo",
    "maxAllowedBlockchainLength": "10",
    "numberOfMonteCarloRounds": "500",
    "blockchainSystemModelFilePath": "org.palladiosimulator.blockchainsystems.trilemma/testmodels/threesim-364/Net.blockchainsystem",
    "failureThroughputThreshold": "1.0",
    "shannonEntropyK": "1.0",
    "nakamotoCoefficientThreshold": "50.0",
    "reliabilityObservationTimespan": "24.0",
    "config_id": "364",
    "id": "364",
    "Hnode": "8.598884456",
    "Hlink": "4.496559465",
    "block_creation_interval": "222",
    "hashrate_concentration": "0.544080638",
    "max_block_size": "5",
    "inbound_connections": "234",
    "outbound_connections": "6",
    "validator_count": "3037",
    "number_of_attackers": "141"
  },
  "simulationResult": {
    "attackerWonRounds": 0,
    "systemWonRounds": 1,
    "unambiguousRounds": 499
  },
  "startSimulationTime": 3117475590107466,
  "stopSimulationTime": 3117500536535261,
  "simulationTime": 24946427795,
  "memoryUsed": 2402
}