{
  "runId": 30,
  "config_id": "30",
  "inputParameters": {
    "simulationType": "Monte-Carlo",
    "maxAllowedBlockchainLength": "10",
    "numberOfMonteCarloRounds": "500",
    "blockchainSystemModelFilePath": "org.palladiosimulator.blockchainsystems.trilemma/testmodels/threesim-30/Net.blockchainsystem",
    "failureThroughputThreshold": "1.0",
    "shannonEntropyK": "1.0",
    "nakamotoCoefficientThreshold": "50.0",
    "reliabilityObservationTimespan": "24.0",
    "config_id": "30",
    "id": "30",
    "Hnode": "0.638071649",
    "Hlink": "8.885055373",
    "block_creation_interval": "53",
    "hashrate_concentration": "0.800158059",
    "max_block_size": "1",
    "inbound_connections": "166",
    "outbound_connections": "2",
    "validator_count": "2303",
    "number_of_attackers": "505"
  },
  "simulationResult": {
    "attackerWonRounds": 0,
    "systemWonRounds": 0,
    "unambiguousRounds": 0,
    "roundResults": []
  },
  "startSimulationTime": 2676192965999730,
  "stopSimulationTime": 2676265900793252,
  "simulationTime": 72934793522,
  "memoryUsed": 24217
}