{
  "runId": 381,
  "config_id": "381",
  "inputParameters": {
    "simulationType": "Monte-Carlo",
    "maxAllowedBlockchainLength": "10",
    "numberOfMonteCarloRounds": "1000",
    "blockchainSystemModelFilePath": "org.palladiosimulator.blockchainsystems.trilemma/testmodels/threesim-381/Net.blockchainsystem",
    "failureThroughputThreshold": "1.0",
    "shannonEntropyK": "1.0",
    "nakamotoCoefficientThreshold": "50.0",
    "reliabilityObservationTimespan": "24.0",
    "config_id": "381",
    "id": "381",
    "Hnode": "8.4979568",
    "Hlink": "0.489223072",
    "block_creation_interval": "905",
    "hashrate_concentration": "0.806931243",
    "max_block_size": "0",
    "inbound_connections": "245",
    "outbound_connections": "4",
    "validator_count": "1266",
    "number_of_attackers": "41"
  },
  "simulationResult": {
    "attackerWonRounds": 0,
    "systemWonRounds": 9,
    "unambiguousRounds": 991
  },
  "startSimulationTime": 3533871006974616,
  "stopSimulationTime": 3533922245080750,
  "simulationTime": 51238106134,
  "memoryUsed": 5261
}