{
  "runId": 39,
  "config_id": "39",
  "inputParameters": {
    "simulationType": "Monte-Carlo",
    "maxAllowedBlockchainLength": "10",
    "numberOfMonteCarloRounds": "1000",
    "blockchainSystemModelFilePath": "org.palladiosimulator.blockchainsystems.trilemma/testmodels/threesim-39/Net.blockchainsystem",
    "failureThroughputThreshold": "1.0",
    "shannonEntropyK": "1.0",
    "nakamotoCoefficientThreshold": "50.0",
    "reliabilityObservationTimespan": "24.0",
    "config_id": "39",
    "id": "39",
    "Hnode": "1.990318051",
    "Hlink": "7.905073654",
    "block_creation_interval": "393",
    "hashrate_concentration": "0.24440977",
    "max_block_size": "8",
    "inbound_connections": "217",
    "outbound_connections": "10",
    "validator_count": "4968",
    "number_of_attackers": "0"
  },
  "simulationResult": {
    "attackerWonRounds": 0,
    "systemWonRounds": 0,
    "unambiguousRounds": 1000
  },
  "startSimulationTime": 3519897221717815,
  "stopSimulationTime": 3519931005525842,
  "simulationTime": 33783808027,
  "memoryUsed": 1540
}