{
  "runId": 166,
  "config_id": "166",
  "inputParameters": {
    "simulationType": "Monte-Carlo",
    "maxAllowedBlockchainLength": "10",
    "numberOfMonteCarloRounds": "500",
    "blockchainSystemModelFilePath": "org.palladiosimulator.blockchainsystems.trilemma/testmodels/threesim-166/Net.blockchainsystem",
    "failureThroughputThreshold": "1.0",
    "shannonEntropyK": "1.0",
    "nakamotoCoefficientThreshold": "50.0",
    "reliabilityObservationTimespan": "24.0",
    "config_id": "166",
    "id": "166",
    "Hnode": "1.821593497",
    "Hlink": "3.540177443",
    "block_creation_interval": "938",
    "hashrate_concentration": "0.234206489",
    "max_block_size": "2",
    "inbound_connections": "78",
    "outbound_connections": "10",
    "validator_count": "530",
    "number_of_attackers": "32"
  },
  "simulationResult": {
    "attackerWonRounds": 0,
    "systemWonRounds": 0,
    "unambiguousRounds": 500
  },
  "startSimulationTime": 3099910569194628,
  "stopSimulationTime": 3100070503557540,
  "simulationTime": 159934362912,
  "memoryUsed": 52578
}