{
  "runId": 312,
  "config_id": "312",
  "inputParameters": {
    "simulationType": "Monte-Carlo",
    "maxAllowedBlockchainLength": "10",
    "numberOfMonteCarloRounds": "500",
    "blockchainSystemModelFilePath": "org.palladiosimulator.blockchainsystems.trilemma/testmodels/threesim-312/Net.blockchainsystem",
    "failureThroughputThreshold": "1.0",
    "shannonEntropyK": "1.0",
    "nakamotoCoefficientThreshold": "50.0",
    "reliabilityObservationTimespan": "24.0",
    "config_id": "312",
    "id": "312",
    "Hnode": "7.009523248",
    "Hlink": "5.683635076",
    "block_creation_interval": "584",
    "hashrate_concentration": "0.979877392",
    "max_block_size": "6",
    "inbound_connections": "45",
    "outbound_connections": "7",
    "validator_count": "4065",
    "number_of_attackers": "294"
  },
  "simulationResult": {
    "attackerWonRounds": 0,
    "systemWonRounds": 0,
    "unambiguousRounds": 500
  },
  "startSimulationTime": 3113256800864321,
  "stopSimulationTime": 3113305665071595,
  "simulationTime": 48864207274,
  "memoryUsed": 9519
}