{
  "runId": 465,
  "config_id": "465",
  "inputParameters": {
    "simulationType": "Monte-Carlo",
    "maxAllowedBlockchainLength": "10",
    "numberOfMonteCarloRounds": "1000",
    "blockchainSystemModelFilePath": "org.palladiosimulator.blockchainsystems.trilemma/testmodels/threesim-465/Net.blockchainsystem",
    "failureThroughputThreshold": "1.0",
    "shannonEntropyK": "1.0",
    "nakamotoCoefficientThreshold": "50.0",
    "reliabilityObservationTimespan": "24.0",
    "config_id": "465",
    "id": "465",
    "Hnode": "3.377456762",
    "Hlink": "8.731062364",
    "block_creation_interval": "496",
    "hashrate_concentration": "0.560202366",
    "max_block_size": "2",
    "inbound_connections": "145",
    "outbound_connections": "3",
    "validator_count": "1441",
    "number_of_attackers": "220"
  },
  "simulationResult": {
    "attackerWonRounds": 0,
    "systemWonRounds": 0,
    "unambiguousRounds": 1000
  },
  "startSimulationTime": 360726226976011,
  "stopSimulationTime": 360746986272913,
  "simulationTime": 20759296902,
  "memoryUsed": 1873
}