{
  "runId": 304,
  "config_id": "304",
  "inputParameters": {
    "simulationType": "Monte-Carlo",
    "maxAllowedBlockchainLength": "10",
    "numberOfMonteCarloRounds": "1000",
    "blockchainSystemModelFilePath": "org.palladiosimulator.blockchainsystems.trilemma/testmodels/threesim-304/Net.blockchainsystem",
    "failureThroughputThreshold": "1.0",
    "shannonEntropyK": "1.0",
    "nakamotoCoefficientThreshold": "50.0",
    "reliabilityObservationTimespan": "24.0",
    "config_id": "304",
    "id": "304",
    "Hnode": "1.177274896",
    "Hlink": "5.646217821",
    "block_creation_interval": "865",
    "hashrate_concentration": "0.517994585",
    "max_block_size": "5",
    "inbound_connections": "81",
    "outbound_connections": "9",
    "validator_count": "2037",
    "number_of_attackers": "461"
  },
  "simulationResult": {
    "attackerWonRounds": 0,
    "systemWonRounds": 2,
    "unambiguousRounds": 998
  },
  "startSimulationTime": 356026151580545,
  "stopSimulationTime": 356066422301766,
  "simulationTime": 40270721221,
  "memoryUsed": 4913
}